CHANGELOG.md
LICENSE.txt
wagtail_sb_fontawesome/__init__.py
wagtail_sb_fontawesome/admin.py
wagtail_sb_fontawesome/apps.py
wagtail_sb_fontawesome/compat.py
wagtail_sb_fontawesome/locale/es/LC_MESSAGES/django.po
wagtail_sb_fontawesome/models.py
wagtail_sb_fontawesome/static/fontawsome/css/font-awesome.css
wagtail_sb_fontawesome/static/fontawsome/css/font-awesome.min.css
wagtail_sb_fontawesome/static/fontawsome/fonts/fontawesome/FontAwesome.otf
wagtail_sb_fontawesome/static/fontawsome/fonts/fontawesome/fontawesome-webfont.eot
wagtail_sb_fontawesome/static/fontawsome/fonts/fontawesome/fontawesome-webfont.svg
wagtail_sb_fontawesome/static/fontawsome/fonts/fontawesome/fontawesome-webfont.ttf
wagtail_sb_fontawesome/static/fontawsome/fonts/fontawesome/fontawesome-webfont.woff
wagtail_sb_fontawesome/static/fontawsome/fonts/fontawesome/fontawesome-webfont.woff2
wagtail_sb_fontawesome/tests.py
wagtail_sb_fontawesome/version.py
wagtail_sb_fontawesome/views.py
wagtail_sb_fontawesome/wagtail_hooks.py
wagtail_sb_fontawesome-0.3.0.dist-info/LICENSE.txt
wagtail_sb_fontawesome-0.3.0.dist-info/METADATA
wagtail_sb_fontawesome-0.3.0.dist-info/WHEEL
wagtail_sb_fontawesome-0.3.0.dist-info/RECORD
