Metadata-Version: 2.1
Name: wagtail-sb-fontawesome
Version: 0.3.0
Summary: FontAwesome for Wagtail Admin.
Home-page: https://gitlab.com/softbutterfly/open-source/wagtail-sb-fontawesome
License: MIT
Keywords: Softbutterfly,Django,Migrations
Author: SoftButterfly Development Team
Author-email: dev@softbutterfly.io
Requires-Python: >=3.8.1,<4.0.0
Classifier: Development Status :: 4 - Beta
Classifier: Environment :: Web Environment
Classifier: Intended Audience :: Developers
Classifier: License :: OSI Approved :: MIT License
Classifier: Natural Language :: English
Classifier: Programming Language :: Python :: 3
Classifier: Programming Language :: Python :: 3.9
Classifier: Programming Language :: Python :: 3.10
Classifier: Programming Language :: Python :: 3.11
Classifier: Programming Language :: Python :: 3.10
Classifier: Programming Language :: Python :: 3.8
Classifier: Programming Language :: Python :: 3.9
Classifier: Topic :: Software Development :: Libraries :: Python Modules
Requires-Dist: django (<5.0)
Requires-Dist: wagtail (<6.0)
Project-URL: Bug Tracker, https://gitlab.com/softbutterfly/open-source/wagtail-sb-fontawesome/-/issues
Project-URL: Documentation, https://gitlab.com/softbutterfly/open-source/wagtail-sb-fontawesome/-/wikis
Project-URL: Download, https://gitlab.com/softbutterfly/open-source/wagtail-sb-fontawesome/-/archive/v0.3.0/wagtail-sb-fontawesome-v0.3.0.tar.gz
Project-URL: Repository, https://gitlab.com/softbutterfly/open-source/wagtail-sb-fontawesome
